eo_lookup_revo.py
eo_lookup_revo-1.0.1.dist-info/DESCRIPTION.rst
eo_lookup_revo-1.0.1.dist-info/METADATA
eo_lookup_revo-1.0.1.dist-info/RECORD
eo_lookup_revo-1.0.1.dist-info/WHEEL
eo_lookup_revo-1.0.1.dist-info/metadata.json
eo_lookup_revo-1.0.1.dist-info/top_level.txt
