Metadata-Version: 2.0
Name: eo-lookup-revo
Version: 1.0.1
Summary: GPL-licensed ReVo content for eo-lookup
Home-page: https://github.com/open-esperanto/eo-lookup-revo
Author: Open Esperanto
Author-email: admin@libraro.net
License: UNKNOWN
Keywords: esperanto revo
Platform: UNKNOWN
Classifier: Development Status :: 4 - Beta
Classifier: Intended Audience :: Developers
Classifier: License :: OSI Approved :: GNU General Public License v2 (GPLv2)
Classifier: Programming Language :: Python :: 3
